telegram_logger/__init__.py
telegram_logger/main.py
telegram_logger_x-0.12a0.dist-info/LICENSE
telegram_logger_x-0.12a0.dist-info/METADATA
telegram_logger_x-0.12a0.dist-info/WHEEL
telegram_logger_x-0.12a0.dist-info/entry_points.txt
telegram_logger_x-0.12a0.dist-info/top_level.txt
telegram_logger_x-0.12a0.dist-info/RECORD
