Metadata-Version: 2.1
Name: telegram-logger-x
Version: 0.12a0
Summary: Logs Telegram events to your console, file(s) or both simultanously.
Home-page: https://github.com/nyuszika7h/telegram-logger
Author: 21st Century Code Bros
Author-email: noreply-use-github-project-page-for-contact@fakemail.com
License: MIT
Download-URL: https://github.com/nyuszika7h/telegram-logger/archive/refs/heads/main.tar.gz
Keywords: Telegram,Logs,logging
Platform: UNKNOWN
Classifier: Development Status :: 3 - Alpha
Classifier: Intended Audience :: Developers
Classifier: Topic :: Software Development :: Build Tools
Classifier: License :: OSI Approved :: MIT License
Classifier: Programming Language :: Python :: 3
Classifier: Programming Language :: Python :: 3.6
Classifier: Programming Language :: Python :: 3.7
Classifier: Programming Language :: Python :: 3.8
Classifier: Programming Language :: Python :: 3.9
License-File: LICENSE
Requires-Dist: telethon
Requires-Dist: toml
